jsonschema_typed/__init__.py
jsonschema_typed/optional_typed_dict.py
jsonschema_typed/plugin.py
jsonschema_typed/py.typed
jsonschema_typed/types.py
jsonschema_typed_v2-0.7.5.dist-info/LICENSE
jsonschema_typed_v2-0.7.5.dist-info/METADATA
jsonschema_typed_v2-0.7.5.dist-info/WHEEL
jsonschema_typed_v2-0.7.5.dist-info/top_level.txt
jsonschema_typed_v2-0.7.5.dist-info/RECORD
