Metadata-Version: 2.1
Name: jsonschema-typed-v2
Version: 0.7.5
Summary: Automatic type annotations from JSON schemas
Home-page: https://github.com/bsamseth/jsonschema-typed
Author: Bendik Samseth
Author-email: b.samseth@gmail.com
License: MIT
Platform: UNKNOWN
Classifier: Development Status :: 4 - Beta
Classifier: Environment :: Console
Classifier: Intended Audience :: Developers
Classifier: License :: OSI Approved :: MIT License
Classifier: Operating System :: OS Independent
Classifier: Programming Language :: Python
Classifier: Programming Language :: Python :: 3.7
Classifier: Programming Language :: Python :: 3.8
Classifier: Programming Language :: Python :: 3 :: Only
Classifier: Topic :: Software Development :: Quality Assurance
Classifier: Topic :: Software Development :: Code Generators
Classifier: Topic :: Software Development :: Testing
Classifier: Typing :: Typed
Requires-Python: >=3.7
Requires-Dist: jsonschema (>=3.2.0)
Requires-Dist: mypy (>=0.761)
